retab/__init__.py
retab/_resource.py
retab/client.py
retab/py.typed
retab/resources/__init__.py
retab/resources/evals.py
retab/resources/files.py
retab/resources/finetuning.py
retab/resources/jsonlUtils.py
retab/resources/models.py
retab/resources/openai_example.py
retab/resources/prompt_optimization.py
retab/resources/schemas.py
retab/resources/usage.py
retab/resources/consensus/__init__.py
retab/resources/consensus/client.py
retab/resources/consensus/completions.py
retab/resources/consensus/completions_stream.py
retab/resources/consensus/responses.py
retab/resources/consensus/responses_stream.py
retab/resources/documents/__init__.py
retab/resources/documents/client.py
retab/resources/documents/extractions.py
retab/resources/evaluations/__init__.py
retab/resources/evaluations/client.py
retab/resources/evaluations/documents.py
retab/resources/evaluations/iterations.py
retab/resources/processors/__init__.py
retab/resources/processors/client.py
retab/resources/processors/automations/__init__.py
retab/resources/processors/automations/client.py
retab/resources/processors/automations/endpoints.py
retab/resources/processors/automations/links.py
retab/resources/processors/automations/logs.py
retab/resources/processors/automations/mailboxes.py
retab/resources/processors/automations/outlook.py
retab/resources/processors/automations/tests.py
retab/resources/secrets/__init__.py
retab/resources/secrets/client.py
retab/resources/secrets/external_api_keys.py
retab/resources/secrets/webhook.py
retab/types/__init__.py
retab/types/ai_models.py
retab/types/browser_canvas.py
retab/types/chat.py
retab/types/completions.py
retab/types/consensus.py
retab/types/evals.py
retab/types/events.py
retab/types/extractions.py
retab/types/inference_settings.py
retab/types/logs.py
retab/types/metrics.py
retab/types/mime.py
retab/types/modalities.py
retab/types/pagination.py
retab/types/predictions.py
retab/types/standards.py
retab/types/automations/__init__.py
retab/types/automations/cron.py
kllms-0.0.42.dist-info/METADATA
kllms-0.0.42.dist-info/WHEEL
kllms-0.0.42.dist-info/top_level.txt
kllms-0.0.42.dist-info/RECORD
